DLR_ICF/DLR_ICF_comparison.py
DLR_ICF/DLR_ICF_gene.py
DLR_ICF/DLR_ICF_main.py
DLR_ICF/DLR_ICF_separation.py
DLR_ICF/ICF_chromatin.py
DLR_ICF/__init__.py
DLR_ICF/__main__.py
DLR_ICF/_version.py
DLR_ICF-1.0.9.dist-info/LICENSE
DLR_ICF-1.0.9.dist-info/METADATA
DLR_ICF-1.0.9.dist-info/WHEEL
DLR_ICF-1.0.9.dist-info/entry_points.txt
DLR_ICF-1.0.9.dist-info/top_level.txt
DLR_ICF-1.0.9.dist-info/RECORD
