Metadata-Version: 2.1
Name: DLR_ICF
Version: 1.0.9
Summary: DLR and ICF analysis
Home-page: https://pypi.org/project/DLR_ICF/
Author: Benxia Hu
Author-email: hubenxia@gmail.com
Classifier: Programming Language :: Python :: 3
Classifier: License :: OSI Approved :: MIT License
Classifier: Operating System :: OS Independent
Requires-Python: >=3.6
License-File: LICENSE
Requires-Dist: numpy
Requires-Dist: pandas
Requires-Dist: argparse
